roadsync_configgy/__init__.py
roadsync_configgy/cli.py
roadsync_configgy/config.py
roadsync_configgy-1.6.2.dist-info/METADATA
roadsync_configgy-1.6.2.dist-info/WHEEL
roadsync_configgy-1.6.2.dist-info/entry_points.txt
roadsync_configgy-1.6.2.dist-info/RECORD
