Metadata-Version: 2.1
Name: roadsync_configgy
Version: 1.6.2
Summary: A simple config file loader that can read values from AWS.
License: MIT
Author: SRE
Author-email: sre@roadsync.com
Requires-Python: >=3.9,<4
Classifier: License :: OSI Approved :: MIT License
Classifier: Programming Language :: Python :: 3
Classifier: Programming Language :: Python :: 3.9
Classifier: Programming Language :: Python :: 3.10
Classifier: Programming Language :: Python :: 3.11
Classifier: Programming Language :: Python :: 3.12
Requires-Dist: boto3 (>1.0.0,<2.0.0)
Requires-Dist: python-box[ruamel-yaml] (>=7.1.1,<8.0.0)
Requires-Dist: ruamel-yaml (>=0.18.10,<0.19.0)
